[{"admin_id":"teamwemmy@gmail.com","w_category_id":1,"host_id":1111000000,"title":"임산부 건강관리","field":"종로구 임산부","content":"1. 임신 12주 이내\n- 임산부초기검사\n-> 모성검사(CBC, 빈혈, 혈액형,성병(VDRL,HIV),B형간염, 풍진검사,소변검사)\n※분만 전 마지막달 검사는 분만병원 이용\n\n2. 임신 10주 ~ 22주\n- 선천성태아기형선별검사(인티그레이티드검사)\n-> 태아의 다운증후군, 에드워드중후군,신경관결손 위험도 확인\n-> 1차 검사: 임신 10주 ~ 13주 6일\n-> 2차 검사: 임신 14주 ~ 22주 6일\n-> 1차 검사전 최근 초음파 검사상 산모체중, NT(목투명대길이)값을 알고 오셔야 합니다.\n\n3. 임신 24주 ∼ 28주\n- 임신성당뇨검사\n-> 검사절차: 2시간 공복 후 내소 → 포도당액 복용 1시간 후 혈액검사\n-> 임신성 당뇨 조기발견\n\n4. 약품제공\n- 엽산제 배부: 임신 12주꺄지\n-> 임신 후 3개월까지 복용 최대 3통\/90일 까지 지원\n- 철분제 배부: 임신 16주부터\n-> 임신 16주 이후 부터 복용 최대 5통\/150일 까지 지원\n\n5. 필요서류\n- 임신확인증 또는 산모수첩, 신분증\n★ 운영시간: 종로구 보건소 2층 모자보건실 \/ 평일 9:00~11:30, 13:00~17:30 접수 운영","way":"- 종로구 보건소 2층 모자보건실 방문\n★ 운영시간: 평일 9:00~11:30, 13:00~17:30 접수 운영","etc":"종로구 보건소 건강증진과 가족건강팀 (02-2148-3595)","original_url":"https:\/\/jongno.go.kr\/Health.do?menuId=4303&menuNo=4303","unique_id":507389618},{"admin_id":"teamwemmy@gmail.com","w_category_id":1,"host_id":1111000000,"title":"유축기 대여","field":"종로구 구민","content":"1. 유축기 대여\n- 모유수유 중인 산모에게 전동 유축기 대여\n- 대여기간: 3개월\n- 대여장소: 중로구 보건소 \/ 동부진료소 (사전전화예약)","way":"- 사전전화 예약후 방문\n-> 종로구 보건소 (02-2148-3595)\n-> 동부진료소 (02-2148-3662)","etc":"종로구 보건소 건강증진과 (02-2148-3595)","original_url":"https:\/\/jongno.go.kr\/Health.do?menuId=4303&menuNo=4303","unique_id":3651152473},{"admin_id":"teamwemmy@gmail.com","w_category_id":2,"host_id":1111000000,"title":"서울종로구육아종합지원센터","field":"종로구민(종로구 소재 직장인)으로 취학 전 아동이 있는 가정","content":"종로구의 영유아가 글로벌리더로 성공할 수 있도록 다양한 놀이 및 교육프로그램을 계획하여 폭넓은 경험의 기회를 제공하며 \"생애보장\" 정신을 바탕으로 보육의 공공성 확보와 투명성을 확립하여 보다 질 높은 보육환경을 조성하고, 학부모 및 보육교직원에게 보육과 관련된 정보와 서비스를 제공함으로써 지역사회에 공헌","way":"서울종로구육아종합지원센터 홈페이지 https:\/\/www.jnccic.or.kr\/main\/index.php 회원가입","etc":"서울종로구육아종합지원센터 (02-737-0890)","original_url":"https:\/\/www.jnccic.or.kr\/main\/index.php","unique_id":9260998826}]